{
  "id": "clue_pipe_wrench_match",
  "title": "The Pipe Wrench in the Boiler House",
  "unlocks": [],
  "category": "physical",
  "createdAt": "2025-07-14T00:00:00Z",
  "updatedAt": "2026-06-13T17:40:35.733Z",
  "locationId": "",
  "scenarioId": "artesian_height_1892",
  "description": "The pipe wrench left on the boiler house floor has its jaws set to a diameter that matches the brake collar adjustment bolt on the drill platform exactly. The wrench handle carries a smear of the same grey rock dust that coats the drill platform — it was used up there before being brought down here. This is the same tool used to tighten the brake collar and, apparently, to attempt an adjustment on the boiler's steam admission valve.",
  "isRedHerring": false,
  "isKeyEvidence": false,
  "discoveryLocationId": "loc_boiler_house",
  "implicatesCharacterIds": [
    "char_silas_greer"
  ]
}